optima_robotics/__init__.py
optima_robotics/robotic.py
optima_robotics-1.0.dist-info/METADATA
optima_robotics-1.0.dist-info/WHEEL
optima_robotics-1.0.dist-info/top_level.txt
optima_robotics-1.0.dist-info/RECORD
