Metadata-Version: 2.1
Name: optima-robotics
Version: 1.0
Summary: A library for robotics.
Home-page: https://github.com/TrungHieuTDC/robotics-lib
Author: TTH
Author-email: trantrunghieu1497@gmail.com
Classifier: Development Status :: 3 - Alpha
Classifier: Intended Audience :: Developers
Classifier: Topic :: Software Development :: Libraries
Classifier: License :: OSI Approved :: MIT License
Classifier: Programming Language :: Python :: 3
Classifier: Programming Language :: Python :: 3.6
Classifier: Programming Language :: Python :: 3.7
Classifier: Programming Language :: Python :: 3.8
Classifier: Programming Language :: Python :: 3.9
Requires-Dist: serial
